README.rst
setup.cfg
setup.py
grip/__init__.py
grip/app.py
grip/cli.py
grip/main.py
grip/model/__init__.py
grip/model/dependency.py
grip/model/graph.py
grip/model/package.py
grip/ui/__init__.py
grip/ui/ansi.py
grip/ui/echo.py
pygrip.egg-info/PKG-INFO
pygrip.egg-info/SOURCES.txt
pygrip.egg-info/dependency_links.txt
pygrip.egg-info/entry_points.txt
pygrip.egg-info/requires.txt
pygrip.egg-info/top_level.txt