Metadata-Version: 1.0
Name: pygrip
Version: 0.3
Summary: Better package management for Python
Home-page: https://eugeny.github.io/grip
Author: Eugene Pankov
Author-email: e@ajenti.org
License: MIT
Platform: UNKNOWN
